Metadata-Version: 1.0
Name: dj-beat
Version: 0.3
Summary: A simple CLI tool for generating beat marks of music for FCPX and PRE
Home-page: http://lidengju.com/dj-beat
Author: Kevin T. Lee
Author-email: hello@lidengju.com
License: MIT
Platform: UNKNOWN
